brainsurfy/__init__.py
brainsurfy/surfplot.py
brainsurfy/utils.py
brainsurfy/atlases/schaefer7_400.csv
brainsurfy-0.0.3.dist-info/LICENSE
brainsurfy-0.0.3.dist-info/METADATA
brainsurfy-0.0.3.dist-info/WHEEL
brainsurfy-0.0.3.dist-info/top_level.txt
brainsurfy-0.0.3.dist-info/RECORD
