Metadata-Version: 2.1
Name: brainsurfy
Version: 0.0.3
Summary: brainsurfy
Home-page: https://github.com/teanijarv/brainsurfy
Author: Toomas Erik Anijärv
Author-email: toomaserikanijarv@gmail.com
License: MIT License
Keywords: brainsurfy
Classifier: Development Status :: 2 - Pre-Alpha
Classifier: Intended Audience :: Developers
Classifier: License :: OSI Approved :: MIT License
Classifier: Natural Language :: English
Classifier: Programming Language :: Python :: 3
Classifier: Programming Language :: Python :: 3.7
Classifier: Programming Language :: Python :: 3.8
Classifier: Programming Language :: Python :: 3.9
Requires-Python: >=3.9
License-File: LICENSE
Requires-Dist: pandas >=1.3.5
Requires-Dist: matplotlib >=3.5.2
Requires-Dist: seaborn >=0.11
